libspud.so
shingle/BRepComponent.py
shingle/Boundary.py
shingle/Bounds.py
shingle/CommandLine.py
shingle/GeoOutput.py
shingle/Import.py
shingle/Mathematical.py
shingle/MeshGenerator.py
shingle/MeshTools.py
shingle/MetricGenerator.py
shingle/OutputFormat.py
shingle/Plot.py
shingle/Prime.py
shingle/Projection.py
shingle/Raster.py
shingle/Reporting.py
shingle/RepresentationTools.py
shingle/SpatialDiscretisation.py
shingle/Spud.py
shingle/StringOperations.py
shingle/Support.py
shingle/SurfaceGeoidDomainRepresentation.py
shingle/Test.py
shingle/Universe.py
shingle/Usage.py
shingle/Version.py
shingle/__init__.py
shingle/OutputFormatWriter/GmshData.py
shingle/OutputFormatWriter/__init__.py
shingle/specific/AntarcticCircumpolarCurrent.py
shingle/specific/Pig.py
shingle/specific/__init__.py
shingle/unittest/test_brml.py
shingle/unittest/test_brml_regions.py
shingle/unittest/test_gmsh_data.py
shingle/unittest/test_list_to_sentence.py
shingle/unittest/test_scientific_netcdf.py
shingle-2.2.0.data/data/AUTHORS
shingle-2.2.0.data/data/COPYING
shingle-2.2.0.data/data/LICENSE
shingle-2.2.0.data/data/README.md
shingle-2.2.0.data/data/shingle_options.rng
shingle-2.2.0.dist-info/METADATA
shingle-2.2.0.dist-info/RECORD
shingle-2.2.0.dist-info/WHEEL
shingle-2.2.0.dist-info/entry_points.txt
shingle-2.2.0.dist-info/top_level.txt
