Metadata-Version: 2.1
Name: shingle
Version: 2.2.0
Summary: Generation of boundary representation and mesh spatial discretisations from arbitrary geophysical fields.
Home-page: http://shingleproject.org
Author: Adam S. Candy
Author-email: contact@shingleproject.org
License: LGPLv3
Keywords: geophysics,meshing,boundary representation,unstructured meshes,mulit-scale modelling,mesh generation,oceanography
Platform: UNKNOWN
Classifier: Development Status :: 4 - Beta
Classifier: Intended Audience :: Science/Research
Classifier: Intended Audience :: Developers
Classifier: Operating System :: OS Independent
Classifier: Programming Language :: Python
Classifier: Programming Language :: Python :: 2
Classifier: Topic :: Scientific/Engineering :: Physics
Classifier: Topic :: Scientific/Engineering :: Mathematics
Classifier: Topic :: Scientific/Engineering :: Atmospheric Science
Classifier: Topic :: Scientific/Engineering :: GIS
Classifier: Topic :: Software Development :: Libraries
Classifier: License :: OSI Approved :: GNU Lesser General Public License v3 (LGPLv3)
Classifier: Programming Language :: Python :: 2.7
Classifier: Programming Language :: C
